secrecy_capacity/__init__.py
secrecy_capacity/calculations_physec.py
secrecy_capacity/low_complexity.py
secrecy_capacity/loyka_algorithm.py
secrecy_capacity/util.py
secrecy_capacity-0.1.0.dist-info/LICENSE
secrecy_capacity-0.1.0.dist-info/METADATA
secrecy_capacity-0.1.0.dist-info/WHEEL
secrecy_capacity-0.1.0.dist-info/top_level.txt
secrecy_capacity-0.1.0.dist-info/RECORD
