Metadata-Version: 2.1
Name: secrecy-capacity
Version: 0.1.0
Summary: Implementation of various algorithms to calculate the secrecy capacity of MIMO channels
Home-page: https://github.com/klb2/secrecy-capacity-calculation
Author: Karl Besser
Author-email: k.besser@tu-bs.de
License: GPLv3
Project-URL: Documentation, https://secrecy-capacity-calculation.readthedocs.io
Project-URL: Source Code, https://github.com/klb2/secrecy-capacity-calculation
Keywords: communications,wiretap channel,secrecy capacity
Platform: UNKNOWN
Classifier: Programming Language :: Python :: 3
Classifier: Intended Audience :: Science/Research
Classifier: Intended Audience :: Telecommunications Industry
Classifier: License :: OSI Approved :: GNU General Public License v3 (GPLv3)
Classifier: Topic :: Scientific/Engineering
License-File: LICENSE
Requires-Dist: numpy
Requires-Dist: scipy
